fpgaconvnet/__init__.py
fpgaconvnet/coefficients/accum_bram.npy
fpgaconvnet/coefficients/accum_dsp.npy
fpgaconvnet/coefficients/accum_ff.npy
fpgaconvnet/coefficients/accum_lut.npy
fpgaconvnet/coefficients/accum_lutlogic.npy
fpgaconvnet/coefficients/accum_lutram.npy
fpgaconvnet/coefficients/concat_bram.npy
fpgaconvnet/coefficients/concat_dsp.npy
fpgaconvnet/coefficients/concat_ff.npy
fpgaconvnet/coefficients/concat_lut.npy
fpgaconvnet/coefficients/conv_bram.npy
fpgaconvnet/coefficients/conv_dsp.npy
fpgaconvnet/coefficients/conv_ff.npy
fpgaconvnet/coefficients/conv_lut.npy
fpgaconvnet/coefficients/eltwise_bram.npy
fpgaconvnet/coefficients/eltwise_dsp.npy
fpgaconvnet/coefficients/eltwise_ff.npy
fpgaconvnet/coefficients/eltwise_lut.npy
fpgaconvnet/coefficients/fork_bram.npy
fpgaconvnet/coefficients/fork_dsp.npy
fpgaconvnet/coefficients/fork_ff.npy
fpgaconvnet/coefficients/fork_lut.npy
fpgaconvnet/coefficients/glue_bram.npy
fpgaconvnet/coefficients/glue_dsp.npy
fpgaconvnet/coefficients/glue_ff.npy
fpgaconvnet/coefficients/glue_lut.npy
fpgaconvnet/coefficients/pool_bram.npy
fpgaconvnet/coefficients/pool_dsp.npy
fpgaconvnet/coefficients/pool_ff.npy
fpgaconvnet/coefficients/pool_lut.npy
fpgaconvnet/coefficients/pool_lutlogic.npy
fpgaconvnet/coefficients/relu_bram.npy
fpgaconvnet/coefficients/relu_dsp.npy
fpgaconvnet/coefficients/relu_ff.npy
fpgaconvnet/coefficients/relu_lut.npy
fpgaconvnet/coefficients/sliding_window_bram.npy
fpgaconvnet/coefficients/sliding_window_dsp.npy
fpgaconvnet/coefficients/sliding_window_ff.npy
fpgaconvnet/coefficients/sliding_window_lut.npy
fpgaconvnet/coefficients/sliding_window_lutlogic.npy
fpgaconvnet/coefficients/sliding_window_lutram.npy
fpgaconvnet/coefficients/sliding_window_lutsr.npy
fpgaconvnet/coefficients/squeeze_bram.npy
fpgaconvnet/coefficients/squeeze_dsp.npy
fpgaconvnet/coefficients/squeeze_ff.npy
fpgaconvnet/coefficients/squeeze_lut.npy
fpgaconvnet/coefficients/squeeze_lutlogic.npy
fpgaconvnet/coefficients/vector_dot_bram.npy
fpgaconvnet_model-0.1.4.2.dist-info/LICENSE
fpgaconvnet_model-0.1.4.2.dist-info/METADATA
fpgaconvnet_model-0.1.4.2.dist-info/WHEEL
fpgaconvnet_model-0.1.4.2.dist-info/top_level.txt
fpgaconvnet_model-0.1.4.2.dist-info/RECORD
