Metadata-Version: 2.1
Name: fpgaconvnet-model
Version: 0.1.4.2
Summary: Parser and model for Convolutional Neural Network Streaming-Based Accelerator on FPGA devices.
Home-page: https://github.com/AlexMontgomerie/fpgaconvnet-model
Author: Alex Montgomerie
Author-email: am9215@ic.ac.uk
Classifier: Programming Language :: Python :: 3
Classifier: Operating System :: OS Independent
Requires-Python: >=3.7
License-File: LICENSE
Requires-Dist: networkx (>=2.5)
Requires-Dist: numpy (>=1.19.2)
Requires-Dist: protobuf (<=3.17.0,>=3.13.0)
Requires-Dist: torch (>=1.7.1)
Requires-Dist: pyyaml (>=5.1.0)
Requires-Dist: scipy (>=1.2.1)
Requires-Dist: torchvision (>=0.8.2)
Requires-Dist: onnx (==1.8.1)
Requires-Dist: onnxruntime (==1.7.0)
Requires-Dist: graphviz (>=0.16)
Requires-Dist: pydot (>=1.4.2)
Requires-Dist: onnxoptimizer (==0.2.6)
Requires-Dist: ddt (>=1.4.2)
Requires-Dist: sklearn
Requires-Dist: matplotlib
Requires-Dist: coverage (==5.5)
Requires-Dist: pyparsing (<3)
